deepsquads_language_data/__init__.py
deepsquads_language_data/admin.py
deepsquads_language_data/aliases.py
deepsquads_language_data/ambiguous.py
deepsquads_language_data/apps.py
deepsquads_language_data/check_languages.py
deepsquads_language_data/countries.py
deepsquads_language_data/country_codes.py
deepsquads_language_data/docs.py
deepsquads_language_data/language_codes.py
deepsquads_language_data/languages.py
deepsquads_language_data/models.py
deepsquads_language_data/plural_tags.py
deepsquads_language_data/plurals.py
deepsquads_language_data/population.py
deepsquads_language_data/rtl.py
deepsquads_language_data/tests.py
deepsquads_language_data/utils.py
deepsquads_language_data/views.py
deepsquads_language_data/locale/django.pot
deepsquads_language_data/locale/ab/LC_MESSAGES/django.mo
deepsquads_language_data/locale/ab/LC_MESSAGES/django.po
deepsquads_language_data/locale/af/LC_MESSAGES/django.mo
deepsquads_language_data/locale/af/LC_MESSAGES/django.po
deepsquads_language_data/locale/afh/LC_MESSAGES/django.mo
deepsquads_language_data/locale/afh/LC_MESSAGES/django.po
deepsquads_language_data/locale/ang/LC_MESSAGES/django.mo
deepsquads_language_data/locale/ang/LC_MESSAGES/django.po
deepsquads_language_data/locale/ar/LC_MESSAGES/django.mo
deepsquads_language_data/locale/ar/LC_MESSAGES/django.po
deepsquads_language_data/locale/ar_LY/LC_MESSAGES/django.mo
deepsquads_language_data/locale/ar_LY/LC_MESSAGES/django.po
deepsquads_language_data/locale/ars/LC_MESSAGES/django.mo
deepsquads_language_data/locale/ars/LC_MESSAGES/django.po
deepsquads_language_data/locale/ast/LC_MESSAGES/django.mo
deepsquads_language_data/locale/ast/LC_MESSAGES/django.po
deepsquads_language_data/locale/az/LC_MESSAGES/django.mo
deepsquads_language_data/locale/az/LC_MESSAGES/django.po
deepsquads_language_data/locale/be/LC_MESSAGES/django.mo
deepsquads_language_data/locale/be/LC_MESSAGES/django.po
deepsquads_language_data/locale/be_Latn/LC_MESSAGES/django.mo
deepsquads_language_data-2024.5.dist-info/LICENSE
deepsquads_language_data-2024.5.dist-info/METADATA
deepsquads_language_data-2024.5.dist-info/WHEEL
deepsquads_language_data-2024.5.dist-info/top_level.txt
deepsquads_language_data-2024.5.dist-info/RECORD
