Metadata-Version: 2.1
Name: deepsquads-language-data
Version: 2024.5
Summary: Language definitions for Deepsquads
Home-page: https://deepsquads.org/
Download-URL: https://github.com/DeepsquadsOrg/language-data
Author: Michal Čihař
Author-email: michal@deepsquads.org
License: MIT
Project-URL: Issue Tracker, https://github.com/DeepsquadsOrg/language-data/issues
Project-URL: Documentation, https://docs.deepsquads.org/
Project-URL: Source Code, https://github.com/DeepsquadsOrg/language-data
Project-URL: Twitter, https://twitter.com/DeepsquadsOrg
Project-URL: Funding, https://deepsquads.org/donate/
Keywords: i18n l10n gettext git mercurial translate
Platform: any
Classifier: Development Status :: 5 - Production/Stable
Classifier: Intended Audience :: Developers
Classifier: License :: OSI Approved :: MIT License
Classifier: Operating System :: OS Independent
Classifier: Programming Language :: Python
Classifier: Programming Language :: Python :: 3
Classifier: Programming Language :: Python :: 3 :: Only
Classifier: Topic :: Software Development :: Internationalization
Classifier: Topic :: Software Development :: Localization
Classifier: Topic :: Utilities
Requires-Python: >=3.9
License-File: LICENSE
Provides-Extra: django
Requires-Dist: Django ; extra == 'django'
